pymdfs/__init__.py
pymdfs/client.py
pymdfs/client_dump.py
pymdfs/client_query.py
pymdfs/latlon.py
pymdfs/config/ElementNameDict.yml
pymdfs/diamond/__init__.py
pymdfs/diamond/diamond1.py
pymdfs/diamond/diamond11.py
pymdfs/diamond/diamond14.py
pymdfs/diamond/diamond16.py
pymdfs/diamond/diamond2.py
pymdfs/diamond/diamond3.py
pymdfs/diamond/diamond31.py
pymdfs/diamond/diamond4.py
pymdfs/diamond/diamond41.py
pymdfs/diamond/diamond42.py
pymdfs/diamond/diamond5.py
pymdfs/diamond/diamond7.py
pymdfs/diamond/diamond8.py
pymdfs/mdfs/DataBlock_pb2.py
pymdfs/mdfs/__init__.py
pymdfs/mdfs/mdfs_grid_data.py
pymdfs/mdfs/mdfs_station_data.py
pymdfs-0.1.1.dist-info/LICENSE
pymdfs-0.1.1.dist-info/METADATA
pymdfs-0.1.1.dist-info/WHEEL
pymdfs-0.1.1.dist-info/entry_points.txt
pymdfs-0.1.1.dist-info/top_level.txt
pymdfs-0.1.1.dist-info/RECORD
