Metadata-Version: 2.1
Name: pymdfs
Version: 0.1.1
Summary: High level python interface to Micaps MDFS Data
Home-page: https://github.com/zjobsdev/PyMDFS
Author: Wenqiang Shen
Author-email: wqshen91@163.com
Requires-Python: >=3.7
License-File: LICENSE
Requires-Dist: awx
Requires-Dist: numpy (>=1.10)
Requires-Dist: xarray
Requires-Dist: pandas
Requires-Dist: logzero (>=1.0)
Requires-Dist: pyyaml
Requires-Dist: protobuf (<=3.20)
Requires-Dist: retrying
Requires-Dist: httplib2netCDF4 (<=1.5.8)
